setup.py
django_celery_task_broker/__init__.py
django_celery_task_broker/serializers.py
django_celery_task_broker/urls.py
django_celery_task_broker/utils.py
django_celery_task_broker.egg-info/PKG-INFO
django_celery_task_broker.egg-info/SOURCES.txt
django_celery_task_broker.egg-info/dependency_links.txt
django_celery_task_broker.egg-info/requires.txt
django_celery_task_broker.egg-info/top_level.txt
django_celery_task_broker/tests/__init__.py
django_celery_task_broker/tests/test_utils.py
django_celery_task_broker/tests/test_views.py
django_celery_task_broker/tests/test_serializers/__init__.py
django_celery_task_broker/tests/test_serializers/test_contrab_schedule_serializer.py
django_celery_task_broker/tests/test_serializers/test_patch_periodic_task_serializer.py
django_celery_task_broker/tests/test_serializers/test_trigger_periodic_task_serializer.py
django_celery_task_broker/tests/test_serializers/test_trigger_task_serializer.py
django_celery_task_broker/views/__init__.py
django_celery_task_broker/views/crontab_schedule_view.py
django_celery_task_broker/views/periodic_task_view.py
django_celery_task_broker/views/trigger_task_view.py
tests/__init__.py
tests/test_utils.py
tests/test_views.py
tests/test_serializers/__init__.py
tests/test_serializers/test_contrab_schedule_serializer.py
tests/test_serializers/test_trigger_periodic_task_serializer.py
tests/test_serializers/test_trigger_task_serializer.py