Metadata-Version: 1.1
Name: django-celery-task-broker
Version: 0.4.0
Summary: A dynamic Django celery task broker
Home-page: https://github.com/prontotools/django-celery-task-broker
Author: Prontotools
Author-email: prontotools@prontomarketing.com
License: MIT License
Platform: UNKNOWN
Classifier: Environment :: Web Environment
Classifier: Framework :: Django
Classifier: Intended Audience :: Developers
Classifier: License :: OSI Approved :: MIT License
Classifier: Programming Language :: Python
Classifier: Programming Language :: Python :: 3.6
Classifier: Topic :: Internet :: WWW/HTTP
Classifier: Topic :: Internet :: WWW/HTTP :: Dynamic Content
